AUTHORS.rst
CONTRIBUTING.rst
HISTORY.rst
LICENSE
README.rst
sklearn_tournament/__init__.py
sklearn_tournament/cli.py
sklearn_tournament-0.1.0.dist-info/entry_points.txt
sklearn_tournament-0.1.0.dist-info/LICENSE
sklearn_tournament-0.1.0.dist-info/WHEEL
sklearn_tournament-0.1.0.dist-info/METADATA
sklearn_tournament-0.1.0.dist-info/RECORD
