Metadata-Version: 2.1
Name: sklearn-tournament
Version: 0.1.0
Summary: Higher level controlls for searching (a collection of) sklearn models for best parameters.
Home-page: https://github.com/sheypex/sklearn-tournament
License: BSD-3-Clause
Author: Sheypex
Author-email: sheypex@gmail.com
Requires-Python: >=3.8,<4.0
Classifier: Development Status :: 2 - Pre-Alpha
Classifier: Intended Audience :: Developers
Classifier: License :: OSI Approved :: BSD License
Classifier: Natural Language :: English
Classifier: Programming Language :: Python :: 3
Classifier: Programming Language :: Python :: 3.8
Classifier: Programming Language :: Python :: 3.9
Project-URL: Bug Tracker, https://github.com/sheypex/sklearn-tournament/issues
Project-URL: Documentation, https://sheypex.github.io/sklearn-tournament/
Project-URL: Repository, https://github.com/sheypex/sklearn-tournament
